gtunrealdevice/__init__.py
gtunrealdevice/__main__.py
gtunrealdevice/application.py
gtunrealdevice/baredevice.py
gtunrealdevice/config.py
gtunrealdevice/constant.py
gtunrealdevice/core.py
gtunrealdevice/example.py
gtunrealdevice/exampledata.yaml
gtunrealdevice/exceptions.py
gtunrealdevice/main.py
gtunrealdevice/operation.py
gtunrealdevice/serialization.py
gtunrealdevice/usage.py
gtunrealdevice/utils.py
gtunrealdevice-0.2.9.dist-info/LICENSE
gtunrealdevice-0.2.9.dist-info/METADATA
gtunrealdevice-0.2.9.dist-info/WHEEL
gtunrealdevice-0.2.9.dist-info/entry_points.txt
gtunrealdevice-0.2.9.dist-info/top_level.txt
gtunrealdevice-0.2.9.dist-info/RECORD
