Metadata-Version: 2.1
Name: gtunrealdevice
Version: 0.2.9
Summary: The application to provide a mock device to test Geeks Trident product.
Home-page: https://github.com/Geeks-Trident-LLC/gtunrealdevice
Author: Tuyen Mathew Duong
Author-email: Tuyen Mathew Duong <tuyen@geekstrident.com>
Maintainer: Tuyen Mathew Duong
Maintainer-email: tuyen@geekstrident.com
License: BSD-3-Clause
Project-URL: Homepage, https://github.com/Geeks-Trident-LLC/gtunrealdevice
Project-URL: Bug Tracker, https://github.com/Geeks-Trident-LLC/gtunrealdevice/issues
Classifier: Development Status :: 2 - Pre-Alpha
Classifier: Intended Audience :: Developers
Classifier: Intended Audience :: End Users/Desktop
Classifier: Intended Audience :: Other Audience
Classifier: Operating System :: MacOS :: MacOS X
Classifier: Operating System :: POSIX :: Linux
Classifier: Operating System :: Microsoft :: Windows
Classifier: License :: OSI Approved :: BSD License
Classifier: Programming Language :: Python
Classifier: Programming Language :: Python :: 3
Classifier: Programming Language :: Python :: 3.6
Classifier: Programming Language :: Python :: 3.7
Classifier: Programming Language :: Python :: 3.8
Classifier: Programming Language :: Python :: 3.9
Classifier: Topic :: Software Development :: Libraries :: Python Modules
Classifier: Topic :: Software Development :: Testing
Requires-Python: >=3.7
License-File: LICENSE
Requires-Dist: pyyaml
